GET/GET_IterAlp.py
GET/__init__.py
GET/main.py
GET/modifiedScheduler.py
GET/subtreePolish.py
GET/treeFunc.py
GET/warmStart.py
GET/ancestorTF_File/ancestorTF_pairs_D1.hdf5
GET/ancestorTF_File/ancestorTF_pairs_D10.hdf5
GET/ancestorTF_File/ancestorTF_pairs_D11.hdf5
GET/ancestorTF_File/ancestorTF_pairs_D12.hdf5
GET/ancestorTF_File/ancestorTF_pairs_D2.hdf5
GET/ancestorTF_File/ancestorTF_pairs_D3.hdf5
GET/ancestorTF_File/ancestorTF_pairs_D4.hdf5
GET/ancestorTF_File/ancestorTF_pairs_D5.hdf5
GET/ancestorTF_File/ancestorTF_pairs_D6.hdf5
GET/ancestorTF_File/ancestorTF_pairs_D7.hdf5
GET/ancestorTF_File/ancestorTF_pairs_D8.hdf5
GET/ancestorTF_File/ancestorTF_pairs_D9.hdf5
get_oblique-0.1.1.dist-info/licenses/LICENSE.md
get_oblique-0.1.1.dist-info/METADATA
get_oblique-0.1.1.dist-info/WHEEL
get_oblique-0.1.1.dist-info/top_level.txt
get_oblique-0.1.1.dist-info/RECORD
