Metadata-Version: 2.4
Name: get-oblique
Version: 0.1.1
Home-page: https://github.com/maoqiangqiang/GET
License-File: LICENSE.md
Requires-Dist: h5py==3.13.0
Requires-Dist: numpy==1.26.4
Requires-Dist: pandas==2.2.3
Requires-Dist: scikit_learn==1.5.0
Requires-Dist: torch>=2.0.0
Dynamic: description
Dynamic: description-content-type
Dynamic: home-page
Dynamic: license-file
Dynamic: requires-dist
